CHANGES.txt
MANIFEST.in
setup.cfg
setup.py
DistChecker.egg-info/PKG-INFO
DistChecker.egg-info/SOURCES.txt
DistChecker.egg-info/dependency_links.txt
DistChecker.egg-info/entry_points.txt
DistChecker.egg-info/requires.txt
DistChecker.egg-info/top_level.txt
DistChecker.egg-info/zip-safe
distchecker/__init__.py
distchecker/describepython.py
distchecker/tests.py