Metadata-Version: 1.1
Name: DistChecker
Version: 1.0
Summary: Helper utiltiies for distutils such as checking the sanity of an sdist
Home-page: http://src.serverzen.com/distchecker
Author: Rocky Burt
Author-email: rocky@serverzen.com
License: UNKNOWN
Keywords: distutils sdist
Platform: UNKNOWN
Classifier: Intended Audience :: Developers
Classifier: Programming Language :: Python
